{"nodes": [{"id": "quickstart_getting_started", "label": "GLIM Getting Started", "file_type": "document", "source_file": "docs/quickstart.md", "source_location": null, "source_url": null, "captured_at": null, "author": null, "contributor": null}, {"id": "quickstart_glim_rosnode", "label": "glim_rosnode Executable", "file_type": "code", "source_file": "docs/quickstart.md", "source_location": null, "source_url": null, "captured_at": null, "author": null, "contributor": null}, {"id": "quickstart_glim_rosbag", "label": "glim_rosbag Executable", "file_type": "code", "source_file": "docs/quickstart.md", "source_location": null, "source_url": null, "captured_at": null, "author": null, "contributor": null}, {"id": "quickstart_config_json", "label": "GLIM JSON Configuration Files", "file_type": "concept", "source_file": "docs/quickstart.md", "source_location": null, "source_url": null, "captured_at": null, "author": null, "contributor": null}, {"id": "quickstart_dump_data", "label": "Mapping Result Dump Data", "file_type": "concept", "source_file": "docs/quickstart.md", "source_location": null, "source_url": null, "captured_at": null, "author": null, "contributor": null}], "edges": [{"source": "quickstart_getting_started", "target": "quickstart_glim_rosnode", "relation": "references", "confidence": "EXTRACTED", "confidence_score": 1.0, "source_file": "docs/quickstart.md", "source_location": null, "weight": 1.0}, {"source": "quickstart_getting_started", "target": "quickstart_glim_rosbag", "relation": "references", "confidence": "EXTRACTED", "confidence_score": 1.0, "source_file": "docs/quickstart.md", "source_location": null, "weight": 1.0}, {"source": "quickstart_getting_started", "target": "quickstart_config_json", "relation": "references", "confidence": "EXTRACTED", "confidence_score": 1.0, "source_file": "docs/quickstart.md", "source_location": null, "weight": 1.0}, {"source": "quickstart_getting_started", "target": "quickstart_dump_data", "relation": "references", "confidence": "EXTRACTED", "confidence_score": 1.0, "source_file": "docs/quickstart.md", "source_location": null, "weight": 1.0}, {"source": "quickstart_getting_started", "target": "installation_install_glim", "relation": "references", "confidence": "EXTRACTED", "confidence_score": 1.0, "source_file": "docs/quickstart.md", "source_location": null, "weight": 1.0}, {"source": "quickstart_getting_started", "target": "parameters_important_params", "relation": "references", "confidence": "EXTRACTED", "confidence_score": 1.0, "source_file": "docs/quickstart.md", "source_location": null, "weight": 1.0}, {"source": "quickstart_config_json", "target": "cmakelists_odometry_estimation_gpu", "relation": "references", "confidence": "EXTRACTED", "confidence_score": 1.0, "source_file": "docs/quickstart.md", "source_location": null, "weight": 1.0}, {"source": "quickstart_config_json", "target": "cmakelists_sub_mapping_passthrough", "relation": "references", "confidence": "EXTRACTED", "confidence_score": 1.0, "source_file": "docs/quickstart.md", "source_location": null, "weight": 1.0}, {"source": "quickstart_config_json", "target": "cmakelists_global_mapping_pose_graph", "relation": "references", "confidence": "EXTRACTED", "confidence_score": 1.0, "source_file": "docs/quickstart.md", "source_location": null, "weight": 1.0}, {"source": "quickstart_dump_data", "target": "merge_offline_viewer", "relation": "references", "confidence": "EXTRACTED", "confidence_score": 1.0, "source_file": "docs/quickstart.md", "source_location": null, "weight": 1.0}], "hyperedges": [{"id": "glim_config_module_selection", "label": "GPU/CPU Config Module Selection", "nodes": ["quickstart_config_json", "cmakelists_odometry_estimation_gpu", "cmakelists_sub_mapping_passthrough", "cmakelists_global_mapping_pose_graph"], "relation": "participate_in", "confidence": "EXTRACTED", "confidence_score": 0.75, "source_file": "docs/quickstart.md"}]}